auth_db_neonix/__init__.py
auth_db_neonix/main.py
auth_db_neonix/version.py
auth_db_neonix/dto/__init__.py
auth_db_neonix/dto/base_settings_dto.py
auth_db_neonix/dto/requests_models_dto.py
auth_db_neonix/dto/user_dto.py
auth_db_neonix/models/__init__.py
auth_db_neonix/models/settings_base_class.py
auth_db_neonix/models/user_model.py
auth_db_neonix/models/user_settings_models.py
auth_db_neonix/services/__init__.py
auth_db_neonix/services/data_retriver_service.py
auth_db_neonix/services/settings_factory.py
auth_db_neonix/services/sqlite_service.py
auth_db_neonix-0.2.2.dist-info/METADATA
auth_db_neonix-0.2.2.dist-info/WHEEL
auth_db_neonix-0.2.2.dist-info/entry_points.txt
auth_db_neonix-0.2.2.dist-info/top_level.txt
auth_db_neonix-0.2.2.dist-info/RECORD
