Metadata-Version: 2.4
Name: auth_db_neonix
Version: 0.2.2
Summary: User auth, settings management, and local DB handling with Firebase and SQLite
Author-email: NeoNix <rittoone@gmail.com>
Requires-Python: >=3.9
Requires-Dist: firebase_admin>=6.9.0
Requires-Dist: pydantic>=1.9.0
Requires-Dist: pandas>=2.0.0
Requires-Dist: cryptography>=45.0.4
Requires-Dist: fastapi>=0.115.12
Requires-Dist: python-dotenv>=1.1.0
Requires-Dist: Requests>=2.32.4
Provides-Extra: dev
Requires-Dist: pytest>=7.0; extra == "dev"
Requires-Dist: flake8>=5.0; extra == "dev"
Requires-Dist: black>=23.0; extra == "dev"
Requires-Dist: mypy>=1.5; extra == "dev"
